{"properties": [
  {
    "name": "keycloak.auth-server-url",
    "type": "java.lang.String",
    "description": "A description for 'keycloak.auth-server-url'"
  },
  {
    "name": "keycloak.realm",
    "type": "java.lang.String",
    "description": "A description for 'keycloak.realm'"
  },
  {
    "name": "keycloak.resource",
    "type": "java.lang.String",
    "description": "A description for 'keycloak.resource'"
  },
  {
    "name": "keycloak.credentials.secret",
    "type": "java.lang.String",
    "description": "A description for 'keycloak.credentials.secret'"
  }
]}